FMU4FOAM/OFFMUBase.py
FMU4FOAM/__init__.py
FMU4FOAM/__main__.py
FMU4FOAM/_version.py
FMU4FOAM/builder.py
FMU4FOAM/of2fmu.py
FMU4FOAM/osutil.py
FMU4FOAM/FMU4FOAM-export/.clang-format
FMU4FOAM/FMU4FOAM-export/CMakeLists.txt
FMU4FOAM/FMU4FOAM-export/build_unix.sh
FMU4FOAM/FMU4FOAM-export/build_win.bat
FMU4FOAM/FMU4FOAM-export/conanfile.py
FMU4FOAM/FMU4FOAM-export/src/CMakeLists.txt
FMU4FOAM/FMU4FOAM-export/src/cppfmu/cppfmu_common.hpp
FMU4FOAM/FMU4FOAM-export/src/cppfmu/cppfmu_cs.cpp
FMU4FOAM/FMU4FOAM-export/src/cppfmu/cppfmu_cs.hpp
FMU4FOAM/FMU4FOAM-export/src/cppfmu/fmi_functions.cpp
FMU4FOAM/FMU4FOAM-export/src/fmi/fmi2FunctionTypes.h
FMU4FOAM/FMU4FOAM-export/src/fmi/fmi2Functions.h
FMU4FOAM/FMU4FOAM-export/src/fmi/fmi2TypesPlatform.h
FMU4FOAM/FMU4FOAM-export/src/fmu4foam/FOAMSlaveInstance.cpp
FMU4FOAM/FMU4FOAM-export/src/fmu4foam/FOAMSlaveInstance.hpp
FMU4FOAM/FMU4FOAM-export/src/fmu4foam/extract.h
FMU4FOAM/resources/binaries/linux64/libfmu4foam-export.so
FMU4FOAM/resources/binaries/win64/fmu4foam-export.dll
FMU4FOAM-1.0.0.dist-info/LICENSE
FMU4FOAM-1.0.0.dist-info/METADATA
FMU4FOAM-1.0.0.dist-info/WHEEL
FMU4FOAM-1.0.0.dist-info/entry_points.txt
FMU4FOAM-1.0.0.dist-info/top_level.txt
FMU4FOAM-1.0.0.dist-info/RECORD
