Metadata-Version: 2.1
Name: FMU4FOAM
Version: 1.0.0
Summary: A lightweight framework that enables the packaging of OpenFOAM as co-simulation FMUs.
Home-page: https://github.com/DLR-RY/FMU4FOAM
Author: Henning Scheufler
License: GPLv3
Keywords: FMI OpenFOAM
Platform: UNKNOWN
Classifier: Development Status :: 3 - Alpha
Classifier: Intended Audience :: End Users/Desktop
Classifier: Intended Audience :: Developers
Classifier: Intended Audience :: Science/Research
Classifier: License :: OSI Approved :: GNU General Public License v3 or later (GPLv3+)
Classifier: Natural Language :: English
Classifier: Programming Language :: C++
Classifier: Programming Language :: Python :: 3 :: Only
Classifier: Programming Language :: Python :: 3.6
Classifier: Programming Language :: Python :: 3.7
Classifier: Programming Language :: Python :: 3.8
Classifier: Programming Language :: Python :: 3.9
Classifier: Topic :: Scientific/Engineering
License-File: LICENSE
